[
  {
    "PersonName": "Asia Duke",
    "Completions": [
      {
        "Name": "X-Ray Safety",
        "Timestamp": "7/5/2023",
        "Expires": null
      }
    ]
  },
  {
    "PersonName": "Zane Mcgrath",
    "Completions": [
      {
        "Name": "Laboratory Safety Training",
        "Timestamp": "7/29/2023",
        "Expires": null
      }
    ]
  },
  {
    "PersonName": "Travis Grant",
    "Completions": [
      {
        "Name": "Laboratory Safety Training",
        "Timestamp": "10/31/2023",
        "Expires": null
      }
    ]
  },
  {
    "PersonName": "Allie Barnes",
    "Completions": [
      {
        "Name": "Electrical Safety for Labs",
        "Timestamp": "8/7/2023",
        "Expires": "8/6/2024"
      }
    ]
  },
  {
    "PersonName": "Brogan Stein",
    "Completions": [
      {
        "Name": "Electrical Safety for Labs",
        "Timestamp": "10/2/2023",
        "Expires": null
      }
    ]
  },
  {
    "PersonName": "Anabelle Braun",
    "Completions": [
      {
        "Name": "X-Ray Safety",
        "Timestamp": "10/24/2023",
        "Expires": null
      }
    ]
  },
  {
    "PersonName": "Cloe Williamson",
    "Completions": [
      {
        "Name": "X-Ray Safety",
        "Timestamp": "8/20/2023",
        "Expires": "8/19/2024"
      }
    ]
  },
  {
    "PersonName": "Nayeli Ortiz",
    "Completions": [
      {
        "Name": "X-Ray Safety",
        "Timestamp": "8/19/2023",
        "Expires": "8/18/2024"
      }
    ]
  },
  {
    "PersonName": "Karli Craig",
    "Completions": [
      {
        "Name": "Laboratory Safety Training",
        "Timestamp": "9/4/2023",
        "Expires": null
      }
    ]
  },
  {
    "PersonName": "Nayeli Mckenzie",
    "Completions": [
      {
        "Name": "Laboratory Safety Training",
        "Timestamp": "8/2/2023",
        "Expires": null
      }
    ]
  },
  {
    "PersonName": "Lexie Ho",
    "Completions": [
      {
        "Name": "Electrical Safety for Labs",
        "Timestamp": "9/28/2023",
        "Expires": null
      }
    ]
  },
  {
    "PersonName": "Jamison Lawson",
    "Completions": [
      {
        "Name": "Electrical Safety for Labs",
        "Timestamp": "8/28/2023",
        "Expires": "8/27/2024"
      }
    ]
  },
  {
    "PersonName": "Zavier Maldonado",
    "Completions": [
      {
        "Name": "Electrical Safety for Labs",
        "Timestamp": "10/11/2023",
        "Expires": null
      }
    ]
  },
  {
    "PersonName": "Ainsley Drake",
    "Completions": [
      {
        "Name": "X-Ray Safety",
        "Timestamp": "8/11/2023",
        "Expires": null
      }
    ]
  },
  {
    "PersonName": "Annabella Jacobson",
    "Completions": [
      {
        "Name": "Laboratory Safety Training",
        "Timestamp": "9/11/2023",
        "Expires": null
      }
    ]
  },
  {
    "PersonName": "Ariella David",
    "Completions": [
      {
        "Name": "Laboratory Safety Training",
        "Timestamp": "8/29/2023",
        "Expires": null
      }
    ]
  },
  {
    "PersonName": "Niko Frey",
    "Completions": [
      {
        "Name": "Laboratory Safety Training",
        "Timestamp": "7/9/2023",
        "Expires": null
      }
    ]
  },
  {
    "PersonName": "Gerald Parsons",
    "Completions": [
      {
        "Name": "Electrical Safety for Labs",
        "Timestamp": "8/28/2023",
        "Expires": "8/27/2024"
      }
    ]
  },
  {
    "PersonName": "Dawson Compton",
    "Completions": [
      {
        "Name": "Laboratory Safety Training",
        "Timestamp": "8/24/2023",
        "Expires": "8/23/2024"
      }
    ]
  },
  {
    "PersonName": "Dania Parrish",
    "Completions": [
      {
        "Name": "Laboratory Safety Training",
        "Timestamp": "7/25/2023",
        "Expires": null
      }
    ]
  },
  {
    "PersonName": "Noah Burch",
    "Completions": [
      {
        "Name": "Laboratory Safety Training",
        "Timestamp": "7/18/2023",
        "Expires": null
      }
    ]
  },
  {
    "PersonName": "Eden Nash",
    "Completions": [
      {
        "Name": "Laboratory Safety Training",
        "Timestamp": "7/16/2023",
        "Expires": "7/15/2024"
      }
    ]
  },
  {
    "PersonName": "Noemi Cisneros",
    "Completions": [
      {
        "Name": "X-Ray Safety",
        "Timestamp": "8/28/2023",
        "Expires": null
      }
    ]
  },
  {
    "PersonName": "Teresa Esparza",
    "Completions": [
      {
        "Name": "Electrical Safety for Labs",
        "Timestamp": "11/2/2023",
        "Expires": "11/1/2024"
      }
    ]
  },
  {
    "PersonName": "Makenzie Pollard",
    "Completions": [
      {
        "Name": "Laboratory Safety Training",
        "Timestamp": "10/25/2023",
        "Expires": null
      }
    ]
  },
  {
    "PersonName": "Calvin Rubio",
    "Completions": [
      {
        "Name": "Electrical Safety for Labs",
        "Timestamp": "10/10/2023",
        "Expires": null
      }
    ]
  },
  {
    "PersonName": "Conner Warner",
    "Completions": [
      {
        "Name": "Laboratory Safety Training",
        "Timestamp": "8/13/2023",
        "Expires": null
      },
      {
        "Name": "Laboratory Safety Training",
        "Timestamp": "8/5/2023",
        "Expires": null
      }
    ]
  },
  {
    "PersonName": "Vaughn Mcmillan",
    "Completions": [
      {
        "Name": "Laboratory Safety Training",
        "Timestamp": "7/29/2023",
        "Expires": null
      }
    ]
  },
  {
    "PersonName": "Gloria Mccarty",
    "Completions": [
      {
        "Name": "X-Ray Safety",
        "Timestamp": "9/26/2023",
        "Expires": "9/25/2024"
      }
    ]
  },
  {
    "PersonName": "Matias Oconnell",
    "Completions": [
      {
        "Name": "Laboratory Safety Training",
        "Timestamp": "7/23/2023",
        "Expires": null
      }
    ]
  },
  {
    "PersonName": "Blaze Joyce",
    "Completions": [
      {
        "Name": "X-Ray Safety",
        "Timestamp": "10/5/2023",
        "Expires": "10/4/2024"
      }
    ]
  },
  {
    "PersonName": "Sasha Armstrong",
    "Completions": [
      {
        "Name": "Laboratory Safety Training",
        "Timestamp": "7/8/2023",
        "Expires": null
      }
    ]
  },
  {
    "PersonName": "Kierra Grimes",
    "Completions": [
      {
        "Name": "Electrical Safety for Labs",
        "Timestamp": "8/6/2023",
        "Expires": null
      }
    ]
  },
  {
    "PersonName": "Hadassah Hampton",
    "Completions": [
      {
        "Name": "X-Ray Safety",
        "Timestamp": "10/25/2023",
        "Expires": "10/24/2024"
      }
    ]
  },
  {
    "PersonName": "Leandro Krause",
    "Completions": [
      {
        "Name": "Electrical Safety for Labs",
        "Timestamp": "11/2/2023",
        "Expires": null
      }
    ]
  },
  {
    "PersonName": "Soren Chaney",
    "Completions": [
      {
        "Name": "X-Ray Safety",
        "Timestamp": "8/25/2023",
        "Expires": null
      }
    ]
  },
  {
    "PersonName": "Reese Raymond",
    "Completions": [
      {
        "Name": "X-Ray Safety",
        "Timestamp": "7/21/2023",
        "Expires": "7/20/2024"
      }
    ]
  },
  {
    "PersonName": "Ann Knight",
    "Completions": [
      {
        "Name": "X-Ray Safety",
        "Timestamp": "10/13/2023",
        "Expires": null
      }
    ]
  },
  {
    "PersonName": "Skye Valenzuela",
    "Completions": [
      {
        "Name": "Laboratory Safety Training",
        "Timestamp": "10/17/2023",
        "Expires": null
      }
    ]
  },
  {
    "PersonName": "Reed Ramos",
    "Completions": [
      {
        "Name": "Electrical Safety for Labs",
        "Timestamp": "8/8/2023",
        "Expires": "8/7/2024"
      }
    ]
  },
  {
    "PersonName": "Armani Tapia",
    "Completions": [
      {
        "Name": "Electrical Safety for Labs",
        "Timestamp": "7/27/2023",
        "Expires": "7/26/2024"
      }
    ]
  },
  {
    "PersonName": "Brynn Marks",
    "Completions": [
      {
        "Name": "X-Ray Safety",
        "Timestamp": "8/3/2023",
        "Expires": "8/2/2024"
      }
    ]
  },
  {
    "PersonName": "Audrina Eaton",
    "Completions": [
      {
        "Name": "Electrical Safety for Labs",
        "Timestamp": "7/26/2023",
        "Expires": null
      }
    ]
  },
  {
    "PersonName": "Charity Lucas",
    "Completions": [
      {
        "Name": "Electrical Safety for Labs",
        "Timestamp": "7/21/2023",
        "Expires": null
      }
    ]
  },
  {
    "PersonName": "Humberto Huerta",
    "Completions": [
      {
        "Name": "Electrical Safety for Labs",
        "Timestamp": "8/23/2023",
        "Expires": null
      }
    ]
  },
  {
    "PersonName": "Rayan Valencia",
    "Completions": [
      {
        "Name": "X-Ray Safety",
        "Timestamp": "9/9/2023",
        "Expires": null
      }
    ]
  },
  {
    "PersonName": "Martin Dean",
    "Completions": [
      {
        "Name": "Electrical Safety for Labs",
        "Timestamp": "8/1/2023",
        "Expires": null
      }
    ]
  },
  {
    "PersonName": "Sandra Manning",
    "Completions": [
      {
        "Name": "Electrical Safety for Labs",
        "Timestamp": "8/29/2023",
        "Expires": null
      }
    ]
  },
  {
    "PersonName": "Destinee Odonnell",
    "Completions": [
      {
        "Name": "X-Ray Safety",
        "Timestamp": "8/6/2023",
        "Expires": null
      }
    ]
  },
  {
    "PersonName": "Lawson Quinn",
    "Completions": [
      {
        "Name": "Laboratory Safety Training",
        "Timestamp": "10/15/2023",
        "Expires": "10/14/2024"
      }
    ]
  },
  {
    "PersonName": "Roy Robbins",
    "Completions": [
      {
        "Name": "Laboratory Safety Training",
        "Timestamp": "7/18/2023",
        "Expires": null
      }
    ]
  },
  {
    "PersonName": "Jagger Hoffman",
    "Completions": [
      {
        "Name": "X-Ray Safety",
        "Timestamp": "9/14/2023",
        "Expires": "9/13/2024"
      }
    ]
  },
  {
    "PersonName": "Kaitlyn Orozco",
    "Completions": [
      {
        "Name": "Laboratory Safety Training",
        "Timestamp": "7/14/2023",
        "Expires": null
      }
    ]
  },
  {
    "PersonName": "Desiree Potts",
    "Completions": [
      {
        "Name": "Electrical Safety for Labs",
        "Timestamp": "10/27/2023",
        "Expires": null
      }
    ]
  },
  {
    "PersonName": "Ezra Powers",
    "Completions": [
      {
        "Name": "X-Ray Safety",
        "Timestamp": "8/13/2023",
        "Expires": "8/12/2024"
      }
    ]
  },
  {
    "PersonName": "Irvin Estrada",
    "Completions": [
      {
        "Name": "X-Ray Safety",
        "Timestamp": "8/5/2023",
        "Expires": null
      }
    ]
  },
  {
    "PersonName": "Mitchell Ware",
    "Completions": [
      {
        "Name": "X-Ray Safety",
        "Timestamp": "9/24/2023",
        "Expires": null
      }
    ]
  },
  {
    "PersonName": "Misael Becker",
    "Completions": [
      {
        "Name": "X-Ray Safety",
        "Timestamp": "7/26/2023",
        "Expires": null
      }
    ]
  },
  {
    "PersonName": "Antwan Villanueva",
    "Completions": [
      {
        "Name": "X-Ray Safety",
        "Timestamp": "9/22/2023",
        "Expires": "9/21/2024"
      },
      {
        "Name": "Electrical Safety for Labs",
        "Timestamp": "10/1/2023",
        "Expires": null
      }
    ]
  }
]